{
    "website": {
      "title": "ScarletBook",
      "publisher": {
        "type": "Organization",
        "name": "Accentio Studios"
      },
      "theme": {
        "name": "wanda",
        "directory": "/system/core/frontend/themes"
      }
    },
    "server": {
        "port": 8080
    },
    "database": {
      "client": "sqlite3",
      "connection": {
        "filename": "/content/database/scarletbook.sqlite"
      },
      "useNullAsDefault": true,
      "migrations": {
        "directory": "/system/core/server/database/migrations"
      },
      "seeds": {
        "directory": "/system/core/server/database/seeds"
      }
    },
    "api": {
        "version": "v1"
    }
}